pertdb/__init__.py
pertdb/models.py
pertdb/types.py
pertdb/migrations/0001_initial.py
pertdb/migrations/__init__.py
pertdb-2.0.2.dist-info/WHEEL
pertdb-2.0.2.dist-info/METADATA
pertdb-2.0.2.dist-info/RECORD
