Metadata-Version: 2.3
Name: pertdb
Version: 2.0.2
Summary: Registries for perturbations and their targets [`source <https://github.com/laminlabs/pertdb/blob/main/pertdb/models.py>`__].
Author-email: Lamin Labs <open-source@lamin.ai>
Requires-Dist: lamindb>=2.0a1,<3
Requires-Dist: bionty>=2.0a1,<3
Requires-Dist: pre-commit ; extra == "dev"
Requires-Dist: nox ; extra == "dev"
Requires-Dist: pytest>=6.0 ; extra == "dev"
Requires-Dist: pytest-cov ; extra == "dev"
Requires-Dist: nbproject_test>=0.4.1 ; extra == "dev"
Project-URL: Home, https://github.com/laminlabs/pertdb
Provides-Extra: dev
